brainome_version.py
version.py
brainome.so
brainome.py
brainome-2.0.172.data/scripts/brainome
brainome-2.0.172.dist-info/WHEEL
brainome-2.0.172.dist-info/top_level.txt
brainome-2.0.172.dist-info/LICENSE
brainome-2.0.172.dist-info/METADATA
brainome-2.0.172.dist-info/RECORD
