Metadata-Version: 2.1
Name: brainome
Version: 2.0.172
Summary: Brainome Table Compiler
Home-page: https://github.com/brainome/examples
Author: Brainome, Inc
Author-email: support@brainome.ai
License: BSD
Classifier: Development Status :: 5 - Production/Stable
Classifier: Environment :: Console
Classifier: Environment :: GPU :: NVIDIA CUDA
Classifier: Intended Audience :: Science/Research
Classifier: Intended Audience :: Developers
Classifier: Intended Audience :: Education
Classifier: License :: OSI Approved :: BSD License
Classifier: Programming Language :: Python :: 3 :: Only
Classifier: Topic :: Scientific/Engineering :: Artificial Intelligence
Classifier: Topic :: Utilities
License-File: LICENSE
Requires-Dist: certifi (>=2021.10.8)
Requires-Dist: requests
Requires-Dist: numpy (>=1.21.5)
Requires-Dist: scikit-learn (<=0.24.2,>=0.22.1)
Requires-Dist: torch (>=1.11.0)
Requires-Dist: Jinja2 (>=3.1.1)
Requires-Dist: xgboost (==1.4.2)
Requires-Dist: packaging (>=21.3)
